zerocap_api_test/__init__.py
zerocap_api_test/main.py
zerocap_api_test-0.1.3.dist-info/LICENSE.txt
zerocap_api_test-0.1.3.dist-info/METADATA
zerocap_api_test-0.1.3.dist-info/WHEEL
zerocap_api_test-0.1.3.dist-info/top_level.txt
zerocap_api_test-0.1.3.dist-info/RECORD
