Metadata-Version: 2.1
Name: zerocap-api-test
Version: 0.1.3
Summary: zerocap_api
Home-page: 
Author: jiayu.gao
Author-email: jiayu.gao@eigen.capital
License: BSD License
Platform: all
Classifier: Programming Language :: Python :: 3
Classifier: License :: OSI Approved :: MIT License
Classifier: Operating System :: OS Independent
Requires-Python: >=3.6
License-File: LICENSE.txt
Requires-Dist: requests
Requires-Dist: websocket
